taxa_sdk/__init__.py
taxa_sdk/browser_ui.py
taxa_sdk/browser_ui_make_js_aes_test.py
taxa_sdk/exceptions.py
taxa_sdk/install_intel_keys.py
taxa_sdk/key_managers.py
taxa_sdk/multihash_py2_py3.py
taxa_sdk/platform_detect.py
taxa_sdk/protocol_installer.py
taxa_sdk/protocol_opener.py
taxa_sdk/taxa_request.py
taxa_sdk/tests.py
taxa_sdk/bin/.DS_Store
taxa_sdk/bin/sp_server.crt
taxa_sdk/bin/taxa-p2p-node
taxa_sdk/bin/taxa-p2p-node.ini
taxa_sdk/bin/taxa-p2p-node_osx
taxa_sdk/bin/taxa_server_check.sh
taxa_sdk/bin/taxaclient.ini
taxa_sdk/bin/Taxa_SDK.App/Contents/Info.plist
taxa_sdk/bin/Taxa_SDK.App/Contents/PkgInfo
taxa_sdk/bin/Taxa_SDK.App/Contents/MacOS/applet
taxa_sdk/bin/libs/OSX/CarbonCore
taxa_sdk/bin/libs/OSX/libSystem.B.dylib
taxa_sdk/bin/libs/OSX/libboost_system.dylib
taxa_sdk/bin/libs/OSX/libboost_thread-mt.dylib
taxa_sdk/bin/libs/OSX/libc++.1.dylib
taxa_sdk/bin/libs/OSX/libcrypto.1.1.dylib
taxa_sdk/bin/libs/OSX/libcurl.4.dylib
taxa_sdk/bin/libs/OSX/liblog4cpp.5.dylib
taxa_sdk/bin/libs/OSX/libobjc.A.dylib
taxa_sdk/bin/libs/OSX/libprotobuf.10.dylib
taxa_sdk/bin/libs/OSX/libprotoc.10.dylib
taxa_sdk/bin/libs/OSX/libservice_provider.so
taxa_sdk/bin/libs/OSX/libssl.1.1.dylib
taxa_sdk/bin/libs/OSX/libsystem_featureflags.dylib
taxa_sdk/bin/libs/OSX/libsystem_malloc.dylib
taxa_sdk/bin/libs/OSX/taxa_client
taxa_sdk/bin/libs/Ubuntu_16.04/ld-linux-x86-64.so.2
taxa_sdk/bin/libs/Ubuntu_16.04/libasn1.so.8
taxa_sdk/bin/libs/Ubuntu_16.04/libboost_system.so.1.58.0
taxa_sdk/bin/libs/Ubuntu_16.04/libc.so.6
taxa_sdk/bin/libs/Ubuntu_16.04/libcom_err.so.2
taxa_sdk/bin/libs/Ubuntu_16.04/libcrypt.so.1
taxa_sdk/bin/libs/Ubuntu_16.04/libcrypto.so.1.0.0
taxa_sdk/bin/libs/Ubuntu_16.04/libcurl.so.4
taxa_sdk/bin/libs/Ubuntu_16.04/libdl.so.2
taxa_sdk/bin/libs/Ubuntu_16.04/libffi.so.6
taxa_sdk/bin/libs/Ubuntu_16.04/libgcc_s.so.1
taxa_sdk/bin/libs/Ubuntu_16.04/libgmp.so.10
taxa_sdk/bin/libs/Ubuntu_16.04/libgnutls.so.30
taxa_sdk/bin/libs/Ubuntu_16.04/libgssapi.so.3
taxa_sdk-0.2.6.dist-info/LICENSE
taxa_sdk-0.2.6.dist-info/METADATA
taxa_sdk-0.2.6.dist-info/WHEEL
taxa_sdk-0.2.6.dist-info/top_level.txt
taxa_sdk-0.2.6.dist-info/RECORD
