Metadata-Version: 2.1
Name: taxa-sdk
Version: 0.2.6
Summary: Developer SDK for the Taxa Network
Home-page: https://github.com/taxa-network/taxa-sdk-python
Author: TF Guo
Author-email: tf@taxa.network
License: LICENSE
Platform: UNKNOWN
Classifier: Development Status :: 5 - Production/Stable
Classifier: Programming Language :: Python
Classifier: Programming Language :: Python :: 2.7
Classifier: Programming Language :: Python :: 3
License-File: LICENSE
Requires-Dist: pyaes
Requires-Dist: requests
Requires-Dist: base58 (==1.0.3)
